runnel/__init__.py
runnel/__main__.py
runnel/app.py
runnel/cli.py
runnel/compression.py
runnel/concurrency.py
runnel/constants.py
runnel/context.py
runnel/discovery.py
runnel/events.py
runnel/exceptions.py
runnel/executor.py
runnel/hashing.py
runnel/interfaces.py
runnel/logging.py
runnel/lua/lock_extend.lua
runnel/lua/lock_release.lua
runnel/middleware/__init__.py
runnel/middleware/ack.py
runnel/middleware/dead.py
runnel/middleware/deserialize.py
runnel/middleware/take.py
runnel/processor.py
runnel/record.py
runnel/runner.py
runnel/serialization.py
runnel/settings.py
runnel/stream.py
runnel/types.py
runnel/utils.py
runnel/worker.py
runnel-0.1.0a6.dist-info/entry_points.txt
runnel-0.1.0a6.dist-info/LICENSE
runnel-0.1.0a6.dist-info/WHEEL
runnel-0.1.0a6.dist-info/METADATA
runnel-0.1.0a6.dist-info/RECORD
