Metadata-Version: 2.1
Name: runnel
Version: 0.1.0a6
Summary: Distributed event processing for Python based on Redis Streams
License: LGPL-3.0-only
Keywords: data,stream,processing,redis,async
Author: Matt Westcott
Author-email: m.westcott@gmail.com
Requires-Python: >=3.8,<4.0
Classifier: License :: OSI Approved :: GNU Lesser General Public License v3 (LGPLv3)
Classifier: Programming Language :: Python :: 3
Classifier: Programming Language :: Python :: 3.8
Provides-Extra: fast
Requires-Dist: aiostream (>=0.4.1,<0.5.0)
Requires-Dist: anyio (>=2.0.0-beta.2,<3.0.0)
Requires-Dist: aredis (>=1.1.8,<2.0.0)
Requires-Dist: colorama (>=0.4.3,<0.5.0)
Requires-Dist: croniter (>=0.3.34,<0.4.0)
Requires-Dist: hiredis (>=1.0.1,<2.0.0)
Requires-Dist: lz4 (>=3.1.0,<4.0.0); extra == "fast"
Requires-Dist: orjson (>=3.2.1,<4.0.0); extra == "fast"
Requires-Dist: pydantic (>=1.5.1,<2.0.0)
Requires-Dist: pytz (>=2020.1,<2021.0)
Requires-Dist: structlog (>=20.1.0,<21.0.0)
Requires-Dist: typer (>=0.3.0,<0.4.0)
Requires-Dist: uvloop (>=0.14.0,<0.15.0); extra == "fast"
Requires-Dist: xxhash (>=1.4.4,<2.0.0); extra == "fast"
